rfs/__init__.py
rfs/py.typed
rfs/analytics/__init__.py
rfs/analytics/charts.py
rfs/analytics/dashboard.py
rfs/analytics/data_source.py
rfs/analytics/kpi.py
rfs/analytics/reports.py
rfs/analytics/visualization.py
rfs/async_tasks/__init__.py
rfs/async_tasks/base.py
rfs/async_tasks/decorators.py
rfs/async_tasks/executor.py
rfs/async_tasks/manager.py
rfs/async_tasks/monitoring.py
rfs/async_tasks/queue.py
rfs/async_tasks/scheduler.py
rfs/async_tasks/task_definition.py
rfs/async_tasks/task_manager.py
rfs/async_tasks/task_result.py
rfs/async_tasks/task_scheduler.py
rfs/cache/__init__.py
rfs/cache/base.py
rfs/cache/decorators.py
rfs/cache/distributed.py
rfs/cache/memory_cache.py
rfs/cache/metrics.py
rfs/cache/redis_cache.py
rfs/cli/__init__.py
rfs/cli/app.py
rfs/cli/core.py
rfs/cli/main.py
rfs/cli/standalone.py
rfs/cli/commands/__init__.py
rfs/cli/commands/basic.py
rfs/cli/commands/debug.py
rfs/cli/commands/deployment.py
rfs/cli/commands/development.py
rfs/cli/commands/project.py
rfs/cli/docs/__init__.py
rfs/cli/docs/generator.py
rfs/cli/testing/__init__.py
rfs/cli/workflows/__init__.py
rfs/cli/workflows/automation.py
rfs/cli/workflows/ci_cd.py
rfs/cloud_run/__init__.py
rfs/cloud_run/autoscaling.py
rfs/cloud_run/helpers.py
rfs/cloud_run/monitoring.py
rfs/cloud_run/service_discovery.py
rfs/cloud_run/task_queue.py
rfs/core/__init__.py
rfs/core/annotation_processor.py
rfs/core/annotation_registry.py
rfs/core/annotations.py
rfs/core/config.py
rfs/core/config_bridge.py
rfs/core/config_profiles.py
rfs/core/config_validation.py
rfs/core/enhanced_logging.py
rfs/core/helpers.py
rfs/core/logging_decorators.py
rfs/core/registry.py
rfs/core/result.py
rfs/core/result.py.backup
rfs/core/singleton.py
rfs/core/transaction_decorators.py
rfs/core/transactions.py
rfs/core/annotations/__init__.py
rfs/core/annotations/base.py
rfs/core/annotations/di.py
rfs/core/annotations/processor.py
rfs/core/annotations/registry.py
rfs/core/transactions/__init__.py
rfs/core/transactions/base.py
rfs_framework-4.6.6.dist-info/METADATA
rfs_framework-4.6.6.dist-info/WHEEL
rfs_framework-4.6.6.dist-info/entry_points.txt
rfs_framework-4.6.6.dist-info/licenses/LICENSE
rfs_framework-4.6.6.dist-info/RECORD
