Metadata-Version: 2.4
Name: rfs-framework
Version: 4.6.6
Summary: Enterprise-Grade Reactive Functional Serverless Framework for Python
Project-URL: Homepage, https://github.com/interactord/rfs-framework
Project-URL: Documentation, https://github.com/interactord/rfs-framework#documentation
Project-URL: Repository, https://github.com/interactord/rfs-framework
Project-URL: Bug Tracker, https://github.com/interactord/rfs-framework/issues
Project-URL: Changelog, https://github.com/interactord/rfs-framework/blob/main/CHANGELOG.md
Author-email: RFS Framework Team <team@rfs-framework.dev>
License: MIT
License-File: LICENSE
Keywords: async,cloud-native,enterprise,framework,functional,microservices,monad,optimization,production-ready,reactive,result-pattern,security,serverless,validation
Classifier: Development Status :: 5 - Production/Stable
Classifier: Framework :: AsyncIO
Classifier: Intended Audience :: Developers
Classifier: License :: OSI Approved :: MIT License
Classifier: Operating System :: OS Independent
Classifier: Programming Language :: Python :: 3
Classifier: Programming Language :: Python :: 3.10
Classifier: Programming Language :: Python :: 3.11
Classifier: Programming Language :: Python :: 3.12
Classifier: Topic :: Internet :: WWW/HTTP :: HTTP Servers
Classifier: Topic :: Software Development :: Libraries :: Application Frameworks
Classifier: Topic :: System :: Distributed Computing
Classifier: Typing :: Typed
Requires-Python: >=3.10
Requires-Dist: aiofiles>=23.2.1
Requires-Dist: asyncio-throttle>=1.0.2
Requires-Dist: click>=8.1.7
Requires-Dist: cryptography>=41.0.0
Requires-Dist: google-cloud-monitoring>=2.16.0
Requires-Dist: google-cloud-run>=0.10.0
Requires-Dist: google-cloud-tasks>=2.15.0
Requires-Dist: prometheus-client>=0.19.0
Requires-Dist: psutil>=5.9.0
Requires-Dist: pydantic<3.0.0,>=2.5.0
Requires-Dist: pyjwt>=2.8.0
Requires-Dist: python-dotenv>=1.0.0
Requires-Dist: rich>=13.7.0
Requires-Dist: superclaude>=4.0.9
Requires-Dist: toml>=0.10.2
Requires-Dist: typer>=0.9.0
Requires-Dist: typing-extensions>=4.8.0
Requires-Dist: watchdog>=3.0.0
Provides-Extra: ai
Requires-Dist: anthropic>=0.7.0; extra == 'ai'
Requires-Dist: openai>=1.3.0; extra == 'ai'
Requires-Dist: transformers>=4.35.0; extra == 'ai'
Provides-Extra: all
Requires-Dist: aiosqlite>=0.19.0; extra == 'all'
Requires-Dist: alembic>=1.13.0; extra == 'all'
Requires-Dist: anthropic>=0.7.0; extra == 'all'
Requires-Dist: asyncpg>=0.29.0; extra == 'all'
Requires-Dist: bandit>=1.7.5; extra == 'all'
Requires-Dist: black>=23.11.0; extra == 'all'
Requires-Dist: faker>=20.1.0; extra == 'all'
Requires-Dist: fastapi>=0.104.0; extra == 'all'
Requires-Dist: flake8>=6.1.0; extra == 'all'
Requires-Dist: gunicorn>=21.2.0; extra == 'all'
Requires-Dist: httpx>=0.25.0; extra == 'all'
Requires-Dist: isort>=5.12.0; extra == 'all'
Requires-Dist: mkdocs-material>=9.4.0; extra == 'all'
Requires-Dist: mkdocs-mermaid2-plugin>=1.1.1; extra == 'all'
Requires-Dist: mkdocs>=1.5.3; extra == 'all'
Requires-Dist: mkdocstrings[python]>=0.24.0; extra == 'all'
Requires-Dist: mypy>=1.7.0; extra == 'all'
Requires-Dist: openai>=1.3.0; extra == 'all'
Requires-Dist: pre-commit>=3.6.0; extra == 'all'
Requires-Dist: pytest-asyncio>=0.21.0; extra == 'all'
Requires-Dist: pytest-cov>=4.1.0; extra == 'all'
Requires-Dist: pytest-mock>=3.12.0; extra == 'all'
Requires-Dist: pytest>=7.4.0; extra == 'all'
Requires-Dist: redis>=5.0.1; extra == 'all'
Requires-Dist: sqlalchemy>=2.0.23; extra == 'all'
Requires-Dist: transformers>=4.35.0; extra == 'all'
Requires-Dist: uvicorn[standard]>=0.24.0; extra == 'all'
Provides-Extra: database
Requires-Dist: aiosqlite>=0.19.0; extra == 'database'
Requires-Dist: alembic>=1.13.0; extra == 'database'
Requires-Dist: asyncpg>=0.29.0; extra == 'database'
Requires-Dist: redis>=5.0.1; extra == 'database'
Requires-Dist: sqlalchemy>=2.0.23; extra == 'database'
Provides-Extra: dev
Requires-Dist: bandit>=1.7.5; extra == 'dev'
Requires-Dist: black>=23.11.0; extra == 'dev'
Requires-Dist: flake8>=6.1.0; extra == 'dev'
Requires-Dist: isort>=5.12.0; extra == 'dev'
Requires-Dist: mypy>=1.7.0; extra == 'dev'
Requires-Dist: pre-commit>=3.6.0; extra == 'dev'
Provides-Extra: docs
Requires-Dist: mkdocs-material>=9.4.0; extra == 'docs'
Requires-Dist: mkdocs-mermaid2-plugin>=1.1.1; extra == 'docs'
Requires-Dist: mkdocs>=1.5.3; extra == 'docs'
Requires-Dist: mkdocstrings[python]>=0.24.0; extra == 'docs'
Provides-Extra: test
Requires-Dist: faker>=20.1.0; extra == 'test'
Requires-Dist: httpx>=0.25.0; extra == 'test'
Requires-Dist: pytest-asyncio>=0.21.0; extra == 'test'
Requires-Dist: pytest-cov>=4.1.0; extra == 'test'
Requires-Dist: pytest-mock>=3.12.0; extra == 'test'
Requires-Dist: pytest>=7.4.0; extra == 'test'
Provides-Extra: web
Requires-Dist: fastapi>=0.104.0; extra == 'web'
Requires-Dist: gunicorn>=21.2.0; extra == 'web'
Requires-Dist: uvicorn[standard]>=0.24.0; extra == 'web'
